pypetal/__init__.py
pypetal/drw_rej/__init__.py
pypetal/drw_rej/module.py
pypetal/drw_rej/utils.py
pypetal/fromfile/__init__.py
pypetal/fromfile/run_toml.py
pypetal/fromfile/write_bash.py
pypetal/mica2/__init__.py
pypetal/mica2/module.py
pypetal/mica2/utils.py
pypetal/pipeline.py
pypetal/pyccf/__init__.py
pypetal/pyccf/module.py
pypetal/pyccf/plotting.py
pypetal/pyccf/utils.py
pypetal/pyroa/__init__.py
pypetal/pyroa/module.py
pypetal/pyroa/plotting.py
pypetal/pyroa/utils.py
pypetal/pyzdcf/__init__.py
pypetal/pyzdcf/module.py
pypetal/pyzdcf/plotting.py
pypetal/pyzdcf/utils.py
pypetal/utils/__init__.py
pypetal/utils/defaults.py
pypetal/utils/detrending.py
pypetal/utils/load.py
pypetal/utils/petalio.py
pypetal/weighting/__init__.py
pypetal/weighting/module.py
pypetal/weighting/plotting.py
pypetal/weighting/utils.py
pypetal-1.0.1.dist-info/LICENSE
pypetal-1.0.1.dist-info/METADATA
pypetal-1.0.1.dist-info/WHEEL
pypetal-1.0.1.dist-info/RECORD
