Metadata-Version: 2.1
Name: pypetal
Version: 1.0.1
Summary: A pipeline for estimating AGN time lags
Home-page: https://github.com/Zstone19/pypetal
License: MIT
Author: Zstone19
Author-email: stone28@illinois.edu
Requires-Python: >=3.8,<3.11
Classifier: Development Status :: 3 - Alpha
Classifier: Environment :: Console
Classifier: Intended Audience :: Science/Research
Classifier: License :: OSI Approved :: MIT License
Classifier: Natural Language :: English
Classifier: Operating System :: POSIX :: Linux
Classifier: Programming Language :: Python :: 3
Classifier: Programming Language :: Python :: 3.8
Classifier: Programming Language :: Python :: 3.9
Classifier: Programming Language :: Python :: 3.10
Classifier: Topic :: Scientific/Engineering :: Astronomy
Classifier: Topic :: Scientific/Engineering :: Physics
Requires-Dist: PyROA (>=3.2.1)
Requires-Dist: astropy (>=5.2.2,<6.0.0)
Requires-Dist: autograd (>=1.5,<2.0)
Requires-Dist: celerite (>=0.4.2,<0.5.0)
Requires-Dist: colorama (>=0.4.6,<0.5.0)
Requires-Dist: corner (>=2.2.1,<3.0.0)
Requires-Dist: emcee (>=3.1.4,<4.0.0)
Requires-Dist: matplotlib (>=3.7.1,<4.0.0)
Requires-Dist: numba (>=0.56.4,<0.57.0)
Requires-Dist: numpy (>=1.19.0,<1.23.0)
Requires-Dist: palettable (>=3.3.0,<4.0.0)
Requires-Dist: pandas (>=1.5.3,<2.0.0)
Requires-Dist: pyzdcf (>=1.0.0,<2.0.0)
Requires-Dist: scipy (>=1.10.1,<2.0.0)
Requires-Dist: tabulate (>=0.9.0,<0.10.0)
Requires-Dist: toml (>=0.10.2,<0.11.0)
Requires-Dist: tqdm (>=4.65.0,<5.0.0)
Project-URL: Documentation, https://pypetal.readthedocs.io
Project-URL: Repository, https://github.com/Zstone19/pypetal
